gql_defrag/__init__.py
gql_defrag/__main__.py
gql_defrag/defrag.py
gql_defrag/finder.py
gql_defrag-0.2.1.dist-info/METADATA
gql_defrag-0.2.1.dist-info/WHEEL
gql_defrag-0.2.1.dist-info/RECORD
