Metadata-Version: 2.3
Name: gql_defrag
Version: 0.2.1
Summary: Merge GraphQL fragments into the parent query
Project-URL: Homepage, https://github.com/JelleZijlstra/gql-defrag
Author-email: Jelle Zijlstra <jelle@quora.com>
Classifier: License :: OSI Approved :: Apache Software License
Classifier: Operating System :: OS Independent
Classifier: Programming Language :: Python :: 3
Requires-Python: >=3.9
Requires-Dist: graphql-core==2.3.2
